passagemath_groups/__init__.py
passagemath_groups.libs/libgap-baf90f0a.so.10
passagemath_groups.libs/libgmp-93ebf16a.so.10.5.0
passagemath_groups.libs/libreadline-28330744.so.8.2
passagemath_groups.libs/libtinfo-f81c2d16.so.6.3
sage/all__sagemath_groups.py
sage/geometry/all__sagemath_groups.py
sage/geometry/palp_normal_form.cpython-314-aarch64-linux-gnu.so
sage/geometry/palp_normal_form.pyx
sage/groups/all.py
sage/groups/all__sagemath_groups.py
sage/groups/artin.py
sage/groups/braid.py
sage/groups/cactus_group.py
sage/groups/cubic_braid.py
sage/groups/finitely_presented.py
sage/groups/finitely_presented_catalog.py
sage/groups/finitely_presented_named.py
sage/groups/fqf_orthogonal.py
sage/groups/free_group.py
sage/groups/group_exp.py
sage/groups/group_semidirect_product.py
sage/groups/kernel_subgroup.py
sage/groups/raag.py
sage/groups/abelian_gps/all.py
sage/groups/lie_gps/all.py
sage/groups/lie_gps/catalog.py
sage/groups/lie_gps/nilpotent_lie_group.py
sage/groups/misc_gps/all.py
sage/groups/misc_gps/misc_groups.py
sage/groups/misc_gps/misc_groups_catalog.py
sage/groups/semimonomial_transformations/all.py
sage/groups/semimonomial_transformations/semimonomial_transformation.cpython-314-aarch64-linux-gnu.so
sage/groups/semimonomial_transformations/semimonomial_transformation.pxd
sage/groups/semimonomial_transformations/semimonomial_transformation.pyx
sage/groups/semimonomial_transformations/semimonomial_transformation_group.py
passagemath_groups-10.6.43.dist-info/METADATA
passagemath_groups-10.6.43.dist-info/WHEEL
passagemath_groups-10.6.43.dist-info/top_level.txt
passagemath_groups-10.6.43.dist-info/RECORD
