Metadata-Version: 2.4
Name: passagemath-groups
Version: 10.6.43
Summary: passagemath: Groups and Invariant Theory
Author-email: The Sage Developers <sage-support@googlegroups.com>
Maintainer: Matthias Köppe, passagemath contributors
License-Expression: GPL-2.0-or-later
Project-URL: release notes, https://github.com/passagemath/passagemath/releases
Project-URL: repo (upstream), https://github.com/sagemath/sage
Project-URL: repo, https://github.com/passagemath/passagemath
Project-URL: documentation, https://passagemath.org/docs/latest
Project-URL: homepage (upstream), https://www.sagemath.org
Project-URL: discourse, https://passagemath.discourse.group
Project-URL: tracker (upstream), https://github.com/sagemath/sage/issues
Project-URL: tracker, https://github.com/passagemath/passagemath/issues
Classifier: Development Status :: 6 - Mature
Classifier: Intended Audience :: Education
Classifier: Intended Audience :: Science/Research
Classifier: Operating System :: POSIX
Classifier: Operating System :: POSIX :: Linux
Classifier: Operating System :: MacOS :: MacOS X
Classifier: Programming Language :: Python :: 3 :: Only
Classifier: Programming Language :: Python :: 3.10
Classifier: Programming Language :: Python :: 3.11
Classifier: Programming Language :: Python :: 3.12
Classifier: Programming Language :: Python :: 3.13
Classifier: Programming Language :: Python :: 3.14
Classifier: Programming Language :: Python :: Implementation :: CPython
Classifier: Topic :: Scientific/Engineering :: Mathematics
Requires-Python: <3.15,>=3.10
Requires-Dist: passagemath-categories~=10.6.43.0
Requires-Dist: passagemath-gap~=10.6.43.0
Requires-Dist: passagemath-modules~=10.6.43.0
Provides-Extra: test
Requires-Dist: passagemath-repl; extra == "test"
Provides-Extra: coxeter3
Requires-Dist: passagemath-coxeter3; extra == "coxeter3"
Provides-Extra: gap
Provides-Extra: additive
Provides-Extra: affine
Provides-Extra: lie
Provides-Extra: matrix
Provides-Extra: permutation
Provides-Extra: presentation
Provides-Extra: representations
Requires-Dist: passagemath-combinat; extra == "representations"
Provides-Extra: semigroups
Requires-Dist: passagemath-combinat; extra == "semigroups"
Provides-Extra: standard
Requires-Dist: passagemath-groups[additive,matrix,representations,semigroups]; extra == "standard"
